yolov9/__init__.py
yolov9-0.0.1.dist-info/METADATA
yolov9-0.0.1.dist-info/WHEEL
yolov9-0.0.1.dist-info/top_level.txt
yolov9-0.0.1.dist-info/RECORD
